cosmos_auth_package/__init__.py
cosmos_auth_package/auth_decorators.py
cosmos_auth_package/schemas.py
cosmos_auth_package/user_verifier.py
cosmos_auth_package-1.0.0.dist-info/METADATA
cosmos_auth_package-1.0.0.dist-info/WHEEL
cosmos_auth_package-1.0.0.dist-info/top_level.txt
cosmos_auth_package-1.0.0.dist-info/RECORD
