Metadata-Version: 2.4
Name: cosmos-auth-package
Version: 1.0.0
Summary: Azure Cosmos DB authentication and user verification package with Flask and FastAPI support. Provides easy-to-use decorators and dependencies for header-based authentication, user verification, role-based access control, and automatic user creation.
Home-page: https://github.com/yourusername/cosmos-auth-package
Author: Your Company Name
Author-email: your.email@example.com
Project-URL: Bug Reports, https://github.com/yourusername/cosmos-auth-package/issues
Project-URL: Source, https://github.com/yourusername/cosmos-auth-package
Project-URL: Documentation, https://github.com/yourusername/cosmos-auth-package#readme
Keywords: cosmos db,azure,authentication,user verification,flask,fastapi,auth,rbac,role-based access control
Classifier: Development Status :: 4 - Beta
Classifier: Intended Audience :: Developers
Classifier: License :: OSI Approved :: MIT License
Classifier: Operating System :: OS Independent
Classifier: Programming Language :: Python :: 3
Classifier: Programming Language :: Python :: 3.8
Classifier: Programming Language :: Python :: 3.9
Classifier: Programming Language :: Python :: 3.10
Classifier: Programming Language :: Python :: 3.11
Classifier: Programming Language :: Python :: 3.12
Classifier: Programming Language :: Python :: 3.13
Requires-Python: >=3.8
Requires-Dist: azure-cosmos>=4.9.0
Provides-Extra: flask
Requires-Dist: flask>=2.0.0; extra == "flask"
Provides-Extra: fastapi
Requires-Dist: fastapi>=0.100.0; extra == "fastapi"
Provides-Extra: all
Requires-Dist: flask>=2.0.0; extra == "all"
Requires-Dist: fastapi>=0.100.0; extra == "all"
Dynamic: author
Dynamic: author-email
Dynamic: classifier
Dynamic: description
Dynamic: description-content-type
Dynamic: home-page
Dynamic: keywords
Dynamic: project-url
Dynamic: provides-extra
Dynamic: requires-dist
Dynamic: requires-python
Dynamic: summary
